odoo/addons/shopinvader_product_brand_tag/README.rst
odoo/addons/shopinvader_product_brand_tag/__init__.py
odoo/addons/shopinvader_product_brand_tag/__manifest__.py
odoo/addons/shopinvader_product_brand_tag/data/ir_export_product.xml
odoo/addons/shopinvader_product_brand_tag/data/ir_export_product_brand.xml
odoo/addons/shopinvader_product_brand_tag/i18n/shopinvader_product_brand_tag.pot
odoo/addons/shopinvader_product_brand_tag/models/__init__.py
odoo/addons/shopinvader_product_brand_tag/models/shopinvader_brand.py
odoo/addons/shopinvader_product_brand_tag/readme/CONTRIBUTORS.rst
odoo/addons/shopinvader_product_brand_tag/readme/DESCRIPTION.rst
odoo/addons/shopinvader_product_brand_tag/static/description/index.html
odoo14_addon_shopinvader_product_brand_tag-14.0.1.0.1.dev3.dist-info/METADATA
odoo14_addon_shopinvader_product_brand_tag-14.0.1.0.1.dev3.dist-info/WHEEL
odoo14_addon_shopinvader_product_brand_tag-14.0.1.0.1.dev3.dist-info/top_level.txt
odoo14_addon_shopinvader_product_brand_tag-14.0.1.0.1.dev3.dist-info/RECORD
